{
  "_meta": {
    "system": "Dopamine 2.0",
    "source_figma": "pk2ZbpG2dylR99ja7M5OkO",
    "last_updated": "2025-05-09",
    "note": "Primitives are lookup-only. Components must reference semantic tokens (color.background.*, color.content.*, etc.)."
  },

  "color": {
    "primitive": {
      "cool-neutral": {
        "0":   { "value": "#000000" },
        "10":  { "value": "#181A1F" },
        "20":  { "value": "#272B33" },
        "30":  { "value": "#414752" },
        "40":  { "value": "#4E5665" },
        "50":  { "value": "#626A7A" },
        "60":  { "value": "#868E9E" },
        "70":  { "value": "#A2A9B8" },
        "80":  { "value": "#BEC5D1" },
        "90":  { "value": "#DDE2EB" },
        "95":  { "value": "#EEF1F5" },
        "97":  { "value": "#F7F8FA" },
        "99":  { "value": "#FBFCFD" },
        "100": { "value": "#FFFFFF" }
      },
      "sunshine-yellow": {
        "10": { "value": "#231D00" },
        "20": { "value": "#3F3101" },
        "30": { "value": "#715A09" },
        "40": { "value": "#967500" },
        "50": { "value": "#BF9514" },
        "60": { "value": "#E8B828" },
        "70": { "value": "#FBD101" },
        "80": { "value": "#FCDD41" },
        "90": { "value": "#FCE880" },
        "95": { "value": "#FFF4C0" },
        "97": { "value": "#FFF9D9" },
        "99": { "value": "#FFFDF2" }
      },
      "sunrise-glow": {
        "10": { "value": "#2B0E03" },
        "20": { "value": "#401504" },
        "30": { "value": "#6F2305" },
        "40": { "value": "#9D3004" },
        "50": { "value": "#CE4009" },
        "60": { "value": "#ED5213" },
        "70": { "value": "#FF6C30" },
        "80": { "value": "#FA8E63" },
        "90": { "value": "#FCB295" },
        "95": { "value": "#FDD7C8" },
        "97": { "value": "#FEE9E1" },
        "99": { "value": "#FFFBFA" }
      },
      "comfort-pink": {
        "20": { "value": "#50132F" },
        "30": { "value": "#772A4D" },
        "40": { "value": "#B1527F" },
        "50": { "value": "#CC749C" },
        "60": { "value": "#E79ABD" },
        "70": { "value": "#F5B2D1" },
        "80": { "value": "#F7C1DA" },
        "90": { "value": "#F9CFE3" },
        "95": { "value": "#FBDEEB" },
        "97": { "value": "#FDECF4" },
        "99": { "value": "#FFFBFD" }
      },
      "healing-mauve": {
        "10": { "value": "#41004B" },
        "20": { "value": "#581463" },
        "30": { "value": "#6E2A79" },
        "40": { "value": "#864291" },
        "50": { "value": "#9D59A8" },
        "60": { "value": "#B470BE" },
        "70": { "value": "#D786E4" },
        "80": { "value": "#EEAAF9" },
        "90": { "value": "#F1BAFA" },
        "95": { "value": "#F5D0FC" },
        "97": { "value": "#FAE5FD" }
      },
      "wellness-green": {
        "10": { "value": "#002C13" },
        "20": { "value": "#004D21" },
        "30": { "value": "#156437" },
        "40": { "value": "#308956" },
        "50": { "value": "#43A46D" },
        "60": { "value": "#63C48D" },
        "70": { "value": "#82D3A5" },
        "80": { "value": "#96DAB3" },
        "90": { "value": "#AFE3C5" },
        "95": { "value": "#C7EDD7" },
        "97": { "value": "#E0F6E9" },
        "99": { "value": "#F8FFFB" }
      },
      "precision-blue": {
        "10": { "value": "#00233F" },
        "20": { "value": "#003E6F" },
        "30": { "value": "#065392" },
        "40": { "value": "#0B66AF" },
        "50": { "value": "#1772BB" },
        "60": { "value": "#2F8AD3" },
        "70": { "value": "#4AA5EE" },
        "80": { "value": "#6BBDFF" },
        "90": { "value": "#8FCDFF" },
        "95": { "value": "#B3DDFF" },
        "97": { "value": "#D6EDFF" },
        "99": { "value": "#ECF8FF" }
      },
      "vital-red": {
        "10": { "value": "#280305" },
        "20": { "value": "#4A050B" },
        "40": { "value": "#A3111E" },
        "60": { "value": "#FD3647" },
        "70": { "value": "#FF6673" },
        "80": { "value": "#FF9EA7" },
        "90": { "value": "#FFB4BB" },
        "95": { "value": "#FFCACF" },
        "97": { "value": "#FFE0E3" }
      },
      "corporate-horizon-blue": {
        "10": { "value": "#002C30" },
        "30": { "value": "#086E78" },
        "40": { "value": "#008F9E" },
        "50": { "value": "#0EB9CB" },
        "60": { "value": "#1AC7D8" },
        "70": { "value": "#38E5F6" },
        "80": { "value": "#6EF2FF" },
        "90": { "value": "#BEF9FF" },
        "95": { "value": "#E5FDFF" },
        "97": { "value": "#EEFEFF" },
        "99": { "value": "#F6FEFF" }
      },
      "golden": {
        "10": { "value": "#E5B674" },
        "20": { "value": "#E8BC7E" },
        "30": { "value": "#EBC288" },
        "40": { "value": "#EEC991" },
        "50": { "value": "#F1CF9B" },
        "70": { "value": "#F6DBAF" },
        "80": { "value": "#F9E2B8" },
        "90": { "value": "#FCE8C2" },
        "95": { "value": "#FFEECC" },
        "97": { "value": "#FFF2D8" },
        "99": { "value": "#FFF6E4" }
      },
      "brown": {
        "30": { "value": "#320A0A" },
        "60": { "value": "#8D7676" },
        "70": { "value": "#9E8B8B" },
        "80": { "value": "#AF9F9F" },
        "90": { "value": "#C0B4B4" },
        "95": { "value": "#D1C8C8" },
        "97": { "value": "#DBD3D3" }
      },
      "white-alpha": {
        "10":  { "value": "#FFFFFF1A" },
        "20":  { "value": "#FFFFFF33" },
        "30":  { "value": "#FFFFFF4D" },
        "40":  { "value": "#FFFFFF66" },
        "50":  { "value": "#FFFFFF80" },
        "60":  { "value": "#FFFFFF99" },
        "70":  { "value": "#FFFFFFB2" },
        "80":  { "value": "#FFFFFFCC" },
        "90":  { "value": "#FFFFFFE5" },
        "95":  { "value": "#FFFFFFF2" },
        "97":  { "value": "#FFFFFFF7" },
        "100": { "value": "#FFFFFF" }
      }
    },

    "background": {
      "primary":  { "value": "#FFFFFF", "css_var": "--color-bg-primary",  "primitive": "cool-neutral.100", "tailwind": "bg-[var(--color-bg-primary)]" },
      "subtle":   { "value": "#EEF1F5", "css_var": "--color-bg-subtle",   "primitive": "cool-neutral.95",  "tailwind": "bg-[var(--color-bg-subtle)]" },
      "moderate": { "value": "#DDE2EB", "css_var": "--color-bg-moderate", "primitive": "cool-neutral.90",  "tailwind": "bg-[var(--color-bg-moderate)]" },
      "disabled": { "value": "#A2A9B8", "css_var": "--color-bg-disabled", "primitive": "cool-neutral.70",  "tailwind": "bg-[var(--color-bg-disabled)]" }
    },

    "content": {
      "primary":   { "value": "#181A1F", "css_var": "--color-content-primary",   "primitive": "cool-neutral.10",  "tailwind": "text-[var(--color-content-primary)]" },
      "secondary": { "value": "#414752", "css_var": "--color-content-secondary", "primitive": "cool-neutral.30",  "tailwind": "text-[var(--color-content-secondary)]" },
      "tertiary":  { "value": "#868E9E", "css_var": "--color-content-tertiary",  "primitive": "cool-neutral.60",  "tailwind": "text-[var(--color-content-tertiary)]" },
      "inverse":   { "value": "#FFFFFF", "css_var": "--color-content-inverse",   "primitive": "cool-neutral.100", "tailwind": "text-[var(--color-content-inverse)]" },
      "disabled":  { "value": "#868E9E", "css_var": "--color-content-disabled",  "primitive": "cool-neutral.60",  "tailwind": "text-[var(--color-content-disabled)]" }
    },

    "border": {
      "subtle":        { "value": "#DDE2EB", "css_var": "--color-border-subtle",        "primitive": "cool-neutral.90", "tailwind": "border-[var(--color-border-subtle)]" },
      "moderate":      { "value": "#BEC5D1", "css_var": "--color-border-moderate",      "primitive": "cool-neutral.80", "tailwind": "border-[var(--color-border-moderate)]" },
      "high-contrast": { "value": "#868E9E", "css_var": "--color-border-high-contrast", "primitive": "cool-neutral.60", "tailwind": "border-[var(--color-border-high-contrast)]" }
    },

    "divider": {
      "subtle":   { "value": "#DDE2EB", "css_var": "--color-border-subtle",   "primitive": "cool-neutral.90", "tailwind": "border-[var(--color-border-subtle)]" },
      "moderate": { "value": "#BEC5D1", "css_var": "--color-border-moderate", "primitive": "cool-neutral.80", "tailwind": "border-[var(--color-border-moderate)]" }
    },

    "state": {
      "success": { "value": "#308956", "css_var": "--color-state-success", "primitive": "wellness-green.40", "tailwind": "text-[var(--color-state-success)]" },
      "offer":   { "value": "#308956", "css_var": "--color-state-offer",   "primitive": "wellness-green.40", "tailwind": "text-[var(--color-state-offer)]" },
      "error":   { "value": "#A3111E", "css_var": "--color-state-error",   "primitive": "vital-red.40",      "tailwind": "text-[var(--color-state-error)]" },
      "warning": { "value": "#BF9514", "css_var": "--color-state-warning", "primitive": "sunshine-yellow.50","tailwind": "text-[var(--color-state-warning)]" }
    },

    "brand": {
      "1mg":           { "value": "#FF5443", "css_var": "--color-brand-1mg",       "primitive": "cool-neutral (Brand/Coral)", "tailwind": "bg-[var(--color-brand-1mg)]" },
      "quick-commerce":{ "value": "#9D59A8", "css_var": "--color-brand-qc",        "primitive": "healing-mauve.50",           "tailwind": "bg-[var(--color-brand-qc)]" },
      "care-plan":     { "value": "#903E38", "css_var": "--color-brand-care",      "primitive": "cool-neutral (Brand/Care Plan)", "tailwind": "bg-[var(--color-brand-care)]" },
      "corporate":     { "value": "#086E78", "css_var": "--color-brand-corporate", "primitive": "corporate-horizon-blue.30",  "tailwind": "bg-[var(--color-brand-corporate)]" }
    },

    "badge": {
      "ember":   { "value": "#C2463E", "css_var": "--color-badge-ember",   "note": "Info badge — warm/promotional label (SPRING/Expressive legacy)" },
      "aqua":    { "value": "#009DA5", "css_var": "--color-badge-aqua",    "note": "Info badge — fresh/health label (SPRING/Sea Foam)" },
      "royal":   { "value": "#6A47B4", "css_var": "--color-badge-royal",   "note": "Info badge — premium/luxury label" },
      "crimson": { "value": "#DA2864", "css_var": "--color-badge-crimson", "note": "Info badge — bold/urgent label" },
      "molten":  { "value": "#5B0400", "css_var": "--color-badge-molten",  "note": "Info badge — deep/rare label (SPRING/Tamarind)" }
    }
  },

  "space": {
    "0":  { "value": "0",     "css_var": "--space-0",  "tailwind": "0"   },
    "2":  { "value": "2px",   "css_var": "--space-2",  "tailwind": "0.5" },
    "4":  { "value": "4px",   "css_var": "--space-4",  "tailwind": "1"   },
    "8":  { "value": "8px",   "css_var": "--space-8",  "tailwind": "2"   },
    "12": { "value": "12px",  "css_var": "--space-12", "tailwind": "3"   },
    "16": { "value": "16px",  "css_var": "--space-16", "tailwind": "4"   },
    "20": { "value": "20px",  "css_var": "--space-20", "tailwind": "5"   },
    "24": { "value": "24px",  "css_var": "--space-24", "tailwind": "6"   },
    "28": { "value": "28px",  "css_var": "--space-28", "tailwind": "7"   },
    "32": { "value": "32px",  "css_var": "--space-32", "tailwind": "8"   },
    "36": { "value": "36px",  "css_var": "--space-36", "tailwind": "9"   },
    "40": { "value": "40px",  "css_var": "--space-40", "tailwind": "10"  }
  },

  "radius": {
    "0":    { "value": "0",      "css_var": "--radius-0",    "tailwind": "rounded-none" },
    "2":    { "value": "2px",    "css_var": "--radius-2",    "tailwind": "rounded-sm"   },
    "4":    { "value": "4px",    "css_var": "--radius-4",    "tailwind": "rounded"      },
    "8":    { "value": "8px",    "css_var": "--radius-8",    "tailwind": "rounded-lg"   },
    "12":   { "value": "12px",   "css_var": "--radius-12",   "tailwind": "rounded-xl"   },
    "16":   { "value": "16px",   "css_var": "--radius-16",   "tailwind": "rounded-2xl"  },
    "24":   { "value": "24px",   "css_var": "--radius-24",   "tailwind": "rounded-3xl"  },
    "full": { "value": "9999px", "css_var": "--radius-full", "tailwind": "rounded-full" }
  },

  "font": {
    "family": {
      "display": { "value": "'Cabinet Grotesk', 'Figtree', system-ui, sans-serif", "css_var": "--font-display", "note": "Display sizes only (24px+). Never below 24px." },
      "sans":    { "value": "'Figtree', system-ui, sans-serif",                     "css_var": "--font-sans",    "note": "Default for all UI text." }
    },
    "size": {
      "display-45": { "value": "45px", "css_var": "--fs-display-45", "tailwind": "text-[45px]" },
      "display-36": { "value": "36px", "css_var": "--fs-display-36", "tailwind": "text-[36px]" },
      "display-24": { "value": "24px", "css_var": "--fs-display-24", "tailwind": "text-2xl"    },
      "heading-32": { "value": "32px", "css_var": "--fs-heading-32", "tailwind": "text-[32px]" },
      "heading-28": { "value": "28px", "css_var": "--fs-heading-28", "tailwind": "text-[28px]" },
      "heading-24": { "value": "24px", "css_var": "--fs-heading-24", "tailwind": "text-2xl"    },
      "heading-18": { "value": "18px", "css_var": "--fs-heading-18", "tailwind": "text-lg"     },
      "title-22":   { "value": "22px", "css_var": "--fs-title-22",   "tailwind": "text-[22px]" },
      "title-16":   { "value": "16px", "css_var": "--fs-title-16",   "tailwind": "text-base"   },
      "body-16":    { "value": "16px", "css_var": "--fs-body-16",    "tailwind": "text-base"   },
      "body-14":    { "value": "14px", "css_var": "--fs-body-14",    "tailwind": "text-sm"     },
      "body-12":    { "value": "12px", "css_var": "--fs-body-12",    "tailwind": "text-xs"     },
      "tag-11":     { "value": "11px", "css_var": "--fs-tag-11",     "tailwind": "text-[11px]" }
    },
    "weight": {
      "light":     { "value": "300", "css_var": "--fw-light",     "tailwind": "font-light"     },
      "regular":   { "value": "400", "css_var": "--fw-regular",   "tailwind": "font-normal"    },
      "medium":    { "value": "500", "css_var": "--fw-medium",    "tailwind": "font-medium"    },
      "bold":      { "value": "700", "css_var": "--fw-bold",      "tailwind": "font-bold"      },
      "extrabold": { "value": "800", "css_var": "--fw-extrabold", "tailwind": "font-extrabold" }
    },
    "line-height": {
      "16": { "value": "16px", "css_var": "--lh-16", "tailwind": "leading-4"      },
      "20": { "value": "20px", "css_var": "--lh-20", "tailwind": "leading-5"      },
      "24": { "value": "24px", "css_var": "--lh-24", "tailwind": "leading-6"      },
      "28": { "value": "28px", "css_var": "--lh-28", "tailwind": "leading-7"      },
      "32": { "value": "32px", "css_var": "--lh-32", "tailwind": "leading-8"      },
      "36": { "value": "36px", "css_var": "--lh-36", "tailwind": "leading-9"      },
      "40": { "value": "40px", "css_var": "--lh-40", "tailwind": "leading-10"     },
      "44": { "value": "44px", "css_var": "--lh-44", "tailwind": "leading-[44px]" },
      "52": { "value": "52px", "css_var": "--lh-52", "tailwind": "leading-[52px]" }
    },
    "letter-spacing": {
      "0": { "value": "0",   "note": "Default — all tokens except Title/12/spaced-700" },
      "3": { "value": "3px", "note": "Title/12/spaced-700 Bold only — all-caps eyebrow labels" }
    }
  },

  "shadow": {
    "1":    { "value": "0 2px 4px 0 rgba(39, 43, 51, 0.06)",  "css_var": "--shadow-1",    "tailwind": "shadow-[0_2px_4px_0_rgba(39,43,51,0.06)]",   "figma_level": "Level 1",      "use": "Resting cards, elevated tiles" },
    "1-iy": { "value": "0 -2px 4px 0 rgba(39, 43, 51, 0.06)", "css_var": "--shadow-1-iy", "tailwind": "shadow-[0_-2px_4px_0_rgba(39,43,51,0.06)]",  "figma_level": "Level 1 (iY)", "use": "Upward-cast, bottom-anchored elements" },
    "2":    { "value": "0 4px 12px 0 rgba(39, 43, 51, 0.08)", "css_var": "--shadow-2",    "tailwind": "shadow-[0_4px_12px_0_rgba(39,43,51,0.08)]",  "figma_level": "Level 2",      "use": "Hover, floating buttons, popovers" },
    "2-iy": { "value": "0 -4px 12px 0 rgba(39, 43, 51, 0.08)","css_var": "--shadow-2-iy", "tailwind": "shadow-[0_-4px_12px_0_rgba(39,43,51,0.08)]", "figma_level": "Level 2 (iY)", "use": "Bottom sheets, upward floating surfaces" }
  }
}
